aotylib/__init__.py
aotylib/functions.py
aotypy-1.dist-info/METADATA
aotypy-1.dist-info/WHEEL
aotypy-1.dist-info/top_level.txt
aotypy-1.dist-info/RECORD
