Metadata-Version: 2.4
Name: aotypy
Version: 1
Summary: get info about albums and artists from albumoftheyear.org
Author: cbhy
Requires-Dist: beautifulsoup4==4.13.4
Requires-Dist: cloudscraper==1.2.71
Requires-Dist: requests==2.32.4
Dynamic: author
Dynamic: requires-dist
Dynamic: summary
